eget_py-1.3.4.data/scripts/eget.exe
eget_py-1.3.4.dist-info/METADATA
eget_py-1.3.4.dist-info/WHEEL
eget_py-1.3.4.dist-info/licenses/LICENSE
eget_py/__init__.py
eget_py-1.3.4.dist-info/RECORD
