Metadata-Version: 2.1
Name: eget-py
Version: 1.3.4
Summary: zyedidia/eget wrapper for python
Keywords: eget,github
Author-Email: dowon <ks2515@naver.com>
Classifier: Programming Language :: Other
Classifier: Topic :: System :: Installation/Setup
Project-URL: Repository, https://github.com/Bing-su/pip-binary-factory
Project-URL: Eget, https://github.com/zyedidia/eget
Requires-Python: >=3.8
